genfiles/__init__.py
genfiles/tool.py
genfiles/tools.py
genfiles/templates/__init__.py
genfiles/templates/base.txt
genfiles/templates/child.txt
genfiles/templates/css.txt
genfiles/templates/data.hjson
genfiles/templates/header.txt
genfiles/templates/item.py
genfiles/templates/items.hjson
genfiles/templates/items.txt
genfiles/templates/macros.txt
genfiles/templates/parent.txt
genfiles-0.0.34.data/scripts/gf_generate
genfiles-0.0.34.data/scripts/gf_generate.cmd
genfiles-0.0.34.data/scripts/gf_help
genfiles-0.0.34.data/scripts/gf_help.cmd
genfiles-0.0.34.dist-info/DESCRIPTION.rst
genfiles-0.0.34.dist-info/METADATA
genfiles-0.0.34.dist-info/RECORD
genfiles-0.0.34.dist-info/WHEEL
genfiles-0.0.34.dist-info/metadata.json
genfiles-0.0.34.dist-info/top_level.txt
